choked/__init__.py
choked/choked.py
choked/test_choked.py
choked/token_bucket/__init__.py
choked/token_bucket/proxy_token_bucket.py
choked/token_bucket/redis_token_bucket.py
choked/token_bucket/test_token_bucket.py
choked-0.2.5.dist-info/METADATA
choked-0.2.5.dist-info/WHEEL
choked-0.2.5.dist-info/top_level.txt
choked-0.2.5.dist-info/RECORD
