Metadata-Version: 2.4
Name: choked
Version: 0.2.5
Summary: A Python rate limiting library
Requires-Python: >=3.8
Requires-Dist: redis
Requires-Dist: python-dotenv
Requires-Dist: pytest-asyncio
Requires-Dist: requests
Requires-Dist: tiktoken
Requires-Dist: transformers
